{
  "schemaVersion": 1,
  "id": "chat_message_confirmation",
  "version": "${version}",
  "name": "Chat Message Confirmation",
  "description": "Displays a confirmation screen when you try to send a chat message or command.",
  "authors": [
    "billzonium_trioxide (SeriousGuy888)"
  ],
  "contact": {
    "issues": "https://github.com/SeriousGuy888/ChatMessageConfirmation/issues",
    "sources": "https://github.com/SeriousGuy888/ChatMessageConfirmation"
  },
  "license": "MIT",
  "icon": "assets/chat_message_confirmation/icon.png",
  "environment": "client",
  "entrypoints": {
    "main": [
      "io.github.seriousguy888.chatmessageconfirmation.ChatMessageConfirmationMod"
    ],
    "modmenu":  [
      "io.github.seriousguy888.chatmessageconfirmation.config.ModMenuIntegration"
    ]
  },
  "mixins": [],
  "depends": {
    "fabricloader": ">=0.16.13",
    "minecraft": "~1.21.5",
    "java": ">=21",
    "fabric-api": "*"
  },
  "recommends": {
    "modmenu": ">=14.0.0"
  }
}